jupy5_mcintyre-0.0.1.data/data/p5_data/sketch.html
p5/__init__.py
p5/sketch.py
jupy5_mcintyre-0.0.1.dist-info/LICENSE
jupy5_mcintyre-0.0.1.dist-info/METADATA
jupy5_mcintyre-0.0.1.dist-info/WHEEL
jupy5_mcintyre-0.0.1.dist-info/top_level.txt
jupy5_mcintyre-0.0.1.dist-info/RECORD
